odoo/addons/l10n_es_pos_oca/README.rst
odoo/addons/l10n_es_pos_oca/__init__.py
odoo/addons/l10n_es_pos_oca/__manifest__.py
odoo/addons/l10n_es_pos_oca/hooks.py
odoo/addons/l10n_es_pos_oca/i18n/ca.po
odoo/addons/l10n_es_pos_oca/i18n/es.po
odoo/addons/l10n_es_pos_oca/i18n/l10n_es_pos.pot
odoo/addons/l10n_es_pos_oca/i18n/l10n_es_pos_oca.pot
odoo/addons/l10n_es_pos_oca/models/__init__.py
odoo/addons/l10n_es_pos_oca/models/ir_sequence.py
odoo/addons/l10n_es_pos_oca/models/pos_config.py
odoo/addons/l10n_es_pos_oca/models/pos_order.py
odoo/addons/l10n_es_pos_oca/models/pos_session.py
odoo/addons/l10n_es_pos_oca/readme/CONFIGURE.md
odoo/addons/l10n_es_pos_oca/readme/CONTRIBUTORS.md
odoo/addons/l10n_es_pos_oca/readme/DESCRIPTION.md
odoo/addons/l10n_es_pos_oca/readme/INSTALL.md
odoo/addons/l10n_es_pos_oca/readme/ROADMAP.md
odoo/addons/l10n_es_pos_oca/static/description/icon.png
odoo/addons/l10n_es_pos_oca/static/description/index.html
odoo/addons/l10n_es_pos_oca/static/src/app/models/pos_order.esm.js
odoo/addons/l10n_es_pos_oca/static/src/app/screens/payment_screen/payment_screen.esm.js
odoo/addons/l10n_es_pos_oca/static/src/app/screens/receipt_screen/receipt/order_receipt.xml
odoo/addons/l10n_es_pos_oca/static/src/app/screens/receipt_screen/receipt/receipt_header/receipt_header.xml
odoo/addons/l10n_es_pos_oca/static/src/app/screens/ticket_screen/ticket_screen.esm.js
odoo/addons/l10n_es_pos_oca/static/src/app/screens/ticket_screen/ticket_screen.xml
odoo/addons/l10n_es_pos_oca/static/src/app/store/pos_store.esm.js
odoo/addons/l10n_es_pos_oca/tests/__init__.py
odoo/addons/l10n_es_pos_oca/tests/test_l10n_es_pos_oca.py
odoo/addons/l10n_es_pos_oca/views/pos_views.xml
odoo/addons/l10n_es_pos_oca/views/res_config_settings_views.xml
odoo/addons/l10n_es_pos_oca/wizard/__init__.py
odoo/addons/l10n_es_pos_oca/wizard/res_config_settings.py
odoo_addon_l10n_es_pos_oca-18.0.1.0.0.3.dist-info/METADATA
odoo_addon_l10n_es_pos_oca-18.0.1.0.0.3.dist-info/WHEEL
odoo_addon_l10n_es_pos_oca-18.0.1.0.0.3.dist-info/top_level.txt
odoo_addon_l10n_es_pos_oca-18.0.1.0.0.3.dist-info/RECORD
