Metadata-Version: 2.1
Name: odoo-addon-l10n_es_pos_oca
Version: 18.0.1.0.0.3
Requires-Python: >=3.10
Requires-Dist: odoo==18.0.*
Summary: =?utf-8?q?Punto_de_venta_adaptado_a_la_legislaci=C3=B3n_espa=C3=B1ola?=
Home-page: https://github.com/OCA/l10n-spain
License: AGPL-3
Author: Tecnativa, Aselcis Consulting, Acysos S.L., Alia Technologies, Odoo Community Association (OCA)
Author-email: support@odoo-community.org
Classifier: Programming Language :: Python
Classifier: Framework :: Odoo
Classifier: Framework :: Odoo :: 18.0
Classifier: License :: OSI Approved :: GNU Affero General Public License v3
